{
  "capacityProviderStrategy": [
    {
      "base": 0,
      "capacityProvider": "FARGATE_SPOT",
      "weight": 1
    }
  ],
  "deploymentConfiguration": {
    "deploymentCircuitBreaker": {
      "enable": false,
      "rollback": false
    },
    "maximumPercent": 200,
    "minimumHealthyPercent": 100
  },
  "desiredCount": 1,
  "enableECSManagedTags": false,
  "enableExecuteCommand": true,
  "healthCheckGracePeriodSeconds": 60,
  "loadBalancers": [
    {
      "containerName": "nginx",
      "containerPort": 80,
      "targetGroupArn": "arn:aws:elasticloadbalancing:ap-northeast-1:522839609870:targetgroup/example-prod-foobar/c258165a7f9af736"
    }
  ],
  "networkConfiguration": {
    "awsvpcConfiguration": {
      "assignPublicIp": "DISABLED",
      "securityGroups": [
        "sg-0b5b4e4a50c1454db"
      ],
      "subnets": [
        "subnet-0ac9a34f021d4c3cc",
        "subnet-0caa4150feb0ab1c8",
        "subnet-030c23382b22aaab4"
      ]
    }
  },
  "placementConstraints": [],
  "placementStrategy": [],
  "platformFamily": "Linux",
  "platformVersion": "1.4.0",
  "schedulingStrategy": "REPLICA",
  "serviceRegistries": [],
  "tags": [
    {
      "key": "Env",
      "value": "prod"
    },
    {
      "key": "System",
      "value": "example"
    },
    {
      "key": "Name",
      "value": "example-prod-foobar"
    }
  ]
}
